marketplacer_lib/__init__.py
marketplacer_lib/gql_client.py
marketplacer_lib/rest_client.py
marketplacer_lib-0.1.3.dist-info/METADATA
marketplacer_lib-0.1.3.dist-info/WHEEL
marketplacer_lib-0.1.3.dist-info/RECORD
