Metadata-Version: 2.1
Name: marketplacer-lib
Version: 0.1.3
Summary: 
Author: Sam Benning
Author-email: sam.b@elitecommercegroup.com
Requires-Python: >=3.12,<4.0
Classifier: Programming Language :: Python :: 3
Classifier: Programming Language :: Python :: 3.12
Requires-Dist: pydantic (>=2.7.4,<3.0.0)
Requires-Dist: python-dotenv (>=1.0.1,<2.0.0)
Requires-Dist: requests (>=2.32.3,<3.0.0)
